lswin/__init__.py
lswin/_macos_window.py
macos_lswin-0.2.dist-info/LICENSE
macos_lswin-0.2.dist-info/METADATA
macos_lswin-0.2.dist-info/WHEEL
macos_lswin-0.2.dist-info/entry_points.txt
macos_lswin-0.2.dist-info/top_level.txt
macos_lswin-0.2.dist-info/RECORD
