Metadata-Version: 2.1
Name: macos-lswin
Version: 0.2
Summary: a commandline utility to list and filter macOS process and window names
Home-page: https://github.com/jwilges/macos-lswin
Author: Jeffrey Wilges
Author-email: jeffrey@wilges.com
License: BSD
Platform: UNKNOWN
Classifier: Development Status :: 2 - Pre-Alpha
Classifier: Environment :: Console
Classifier: License :: OSI Approved :: BSD License
Classifier: Operating System :: MacOS :: MacOS X
Classifier: Programming Language :: Python :: 3
Classifier: Topic :: Utilities
Requires-Python: >=3.6
Requires-Dist: pyobjc-framework-Quartz (==6.1) ; platform_system == "Darwin"
